certbot_dns_cloudns/__init__.py
certbot_dns_cloudns/_internal/__init__.py
certbot_dns_cloudns/_internal/authenticator.py
certbot_dns_cloudns/_internal/client.py
certbot_dns_cloudns/_internal/resolve.py
certbot_dns_cloudns/_internal/tests/__init__.py
certbot_dns_cloudns/_internal/tests/authenticator_test.py
certbot_dns_cloudns-0.7.0.dist-info/LICENSE
certbot_dns_cloudns-0.7.0.dist-info/METADATA
certbot_dns_cloudns-0.7.0.dist-info/WHEEL
certbot_dns_cloudns-0.7.0.dist-info/entry_points.txt
certbot_dns_cloudns-0.7.0.dist-info/RECORD
