Metadata-Version: 2.1
Name: certbot-dns-cloudns
Version: 0.7.0
Summary: ClouDNS DNS Authenticator plugin for Certbot
Home-page: https://github.com/inventage/certbot-dns-cloudns
License: Unlicense
Author: Simon Marti
Author-email: simon.marti@inventage.com
Requires-Python: >=3.8,<4.0
Classifier: Development Status :: 3 - Alpha
Classifier: Environment :: Plugins
Classifier: Intended Audience :: System Administrators
Classifier: License :: OSI Approved
Classifier: License :: OSI Approved :: The Unlicense (Unlicense)
Classifier: Operating System :: OS Independent
Classifier: Programming Language :: Python :: 3
Classifier: Programming Language :: Python :: 3.8
Classifier: Programming Language :: Python :: 3.9
Classifier: Programming Language :: Python :: 3.10
Classifier: Programming Language :: Python :: 3.11
Classifier: Programming Language :: Python :: 3.12
Classifier: Topic :: Internet :: Name Service (DNS)
Classifier: Topic :: Internet :: WWW/HTTP
Classifier: Topic :: Security
Classifier: Topic :: System :: Installation/Setup
Classifier: Topic :: System :: Networking
Classifier: Topic :: System :: Systems Administration
Classifier: Topic :: Utilities
Requires-Dist: acme (>=2.11.0)
Requires-Dist: certbot (>=2.11.0)
Requires-Dist: cloudns-api (==0.9.3)
Requires-Dist: dnspython (>=2.3.0)
Requires-Dist: zope.interface (>=5.4.0)
Project-URL: Repository, https://github.com/inventage/certbot-dns-cloudns
